pylcmodel/__init__.py
pylcmodel/_lcmodel.py
pylcmodel/_version.py
pylcmodel/cli.py
pylcmodel/namelist.py
pylcmodel-0.3.3.dist-info/LICENSE
pylcmodel-0.3.3.dist-info/METADATA
pylcmodel-0.3.3.dist-info/WHEEL
pylcmodel-0.3.3.dist-info/entry_points.txt
pylcmodel-0.3.3.dist-info/top_level.txt
pylcmodel-0.3.3.dist-info/RECORD
